mc_wordcloud/__init__.py
mc_wordcloud/hero_name.txt
mc_wordcloud/mc_wordcloud.py
mc_wordcloud/tool_list.txt
mc_wordcloud/weapon_list.txt
mc_wordcloud-0.1.0.data/data/mc_wordcloud/hero_name.txt
mc_wordcloud-0.1.0.data/data/mc_wordcloud/tool_list.txt
mc_wordcloud-0.1.0.data/data/mc_wordcloud/weapon_list.txt
mc_wordcloud-0.1.0.dist-info/LICENSE
mc_wordcloud-0.1.0.dist-info/METADATA
mc_wordcloud-0.1.0.dist-info/WHEEL
mc_wordcloud-0.1.0.dist-info/top_level.txt
mc_wordcloud-0.1.0.dist-info/RECORD
